tests/__init__.py
tests/test_models.py
veracodetocsv/__init__.py
veracodetocsv/__main__.py
veracodetocsv/veracodetocsv.py
veracodetocsv/helpers/__init__.py
veracodetocsv/helpers/api.py
veracodetocsv/helpers/api_hmac.py
veracodetocsv/helpers/build.py
veracodetocsv/helpers/data.py
veracodetocsv/helpers/exceptions.py
veracodetocsv/helpers/log.py
veracodetocsv/helpers/models.py
veracodetocsv/helpers/unicodecsv.py
veracodetocsv-2020.4.0.dist-info/METADATA
veracodetocsv-2020.4.0.dist-info/WHEEL
veracodetocsv-2020.4.0.dist-info/entry_points.txt
veracodetocsv-2020.4.0.dist-info/top_level.txt
veracodetocsv-2020.4.0.dist-info/RECORD
